multiconfparse/__init__.py
multiconfparse/multiconfparse.py
multiconfparse-0.1.0.dist-info/LICENSE
multiconfparse-0.1.0.dist-info/METADATA
multiconfparse-0.1.0.dist-info/WHEEL
multiconfparse-0.1.0.dist-info/top_level.txt
multiconfparse-0.1.0.dist-info/RECORD
